{
  "$schema": "https://biomejs.dev/schemas/1.9.4/schema.json",
  "vcs": {
    "enabled": false,
    "clientKind": "git",
    "useIgnoreFile": false
  },
  "files": {
    "ignoreUnknown": false,
    "ignore": ["dist", ".next", "node_modules", "build", "src/generated/**"],
    "include": ["src/**/*.ts", "src/**/*.tsx"]
  },
  "formatter": {
    "enabled": true,
    "indentStyle": "space"
  },
  "organizeImports": {
    "enabled": true
  },
  "linter": {
    "enabled": true,
    "rules": {
      "recommended": true,
      "correctness": {
        "noUnusedVariables": "off"
      },
      "nursery": {
        "noImgElement": "off"
      },
      "a11y": {
        "useAltText": "off"
      },
      "suspicious": {
        "noExplicitAny": "off"
      }
    }
  },
  "javascript": {
    "formatter": {
      "quoteStyle": "double"
    }
  }
}